multiloan/__init__.py
multiloan/loans.py
multiloan/utils.py
multiloan-0.5.dist-info/LICENSE
multiloan-0.5.dist-info/METADATA
multiloan-0.5.dist-info/WHEEL
multiloan-0.5.dist-info/top_level.txt
multiloan-0.5.dist-info/RECORD
