Metadata-Version: 2.1
Name: multiloan
Version: 0.5
Summary: Tools for managing loan payments
Home-page: UNKNOWN
Author: michaelsilverstein
Author-email: michael.silverstein4@gmail.com
License: MIT
Platform: UNKNOWN
Requires-Dist: numpy
Requires-Dist: pandas
